sshlist/__init__.py
sshlist/screen.py
sshlist/sshlist.py
sshlist_cli-1.0.0.dist-info/LICENSE
sshlist_cli-1.0.0.dist-info/METADATA
sshlist_cli-1.0.0.dist-info/WHEEL
sshlist_cli-1.0.0.dist-info/entry_points.txt
sshlist_cli-1.0.0.dist-info/top_level.txt
sshlist_cli-1.0.0.dist-info/RECORD
